MANIFEST.in
README.md
setup.py
parrot/__init__.py
parrot/cli.py
parrot/frames/0.txt
parrot/frames/1.txt
parrot/frames/2.txt
parrot/frames/3.txt
parrot/frames/4.txt
parrot/frames/5.txt
parrot/frames/6.txt
parrot/frames/7.txt
parrot/frames/8.txt
parrot/frames/9.txt
parrot_terminal.egg-info/PKG-INFO
parrot_terminal.egg-info/SOURCES.txt
parrot_terminal.egg-info/dependency_links.txt
parrot_terminal.egg-info/entry_points.txt
parrot_terminal.egg-info/requires.txt
parrot_terminal.egg-info/top_level.txt