Metadata-Version: 1.1
Name: parrot-terminal
Version: 0.3
Summary: PARTY OR DIE
Home-page: https://github.com/daenylio/asciimation
Author: Tuan Nguyen
Author-email: tuan.nguyenviet271@gmail.com
License: UNKNOWN
Platform: UNKNOWN
Classifier: Programming Language :: Python :: 3
Classifier: License :: OSI Approved :: MIT License
